aimet_common/__init__.py
aimet_torch/__init__.py
aimet_torch/auto_quant.py
aimet_torch/batch_norm_fold.py
aimet_torch/bias_correction.py
aimet_torch/blockwise_sampler.py
aimet_torch/bn_reestimation.py
aimet_torch/compress.py
aimet_torch/compression_factory.py
aimet_torch/cost_calculator.py
aimet_torch/cross_layer_equalization.py
aimet_torch/data_subsampler.py
aimet_torch/defs.py
aimet_torch/elementwise_ops.py
aimet_torch/fp_quantization.py
aimet_torch/layer_database.py
aimet_torch/layer_output_utils.py
aimet_torch/layer_selector.py
aimet_torch/mixed_precision.py
aimet_torch/model_preparer.py
aimet_torch/onnx.py
aimet_torch/onnx_utils.py
aimet_torch/peft.py
aimet_torch/plots.py
aimet_torch/plotting_utils.py
aimet_torch/qc_quantize_op.py
aimet_torch/qc_quantize_recurrent.py
aimet_torch/quant_analyzer.py
aimet_torch/quantsim.py
aimet_torch/quantsim_straight_through_grad.py
aimet_torch/save_utils.py
aimet_torch/seq_mse.py
aimet_torch/tensor_factory_utils.py
aimet_torch/tensor_quantizer.py
aimet_torch/torch_quantizer.py
aimet_torch/torchscript_utils.py
aimet_torch/translation_mapping.py
aimet_torch/utils.py
aimet_torch/visualize_model.py
aimet_torch/visualize_serialized_data.py
aimet_torch/weight_padding_utils.py
aimet_torch/_base/__init__.py
aimet_torch/_base/auto_quant.py
aimet_torch/_base/auto_quant_diagnostics_template.css
aimet_torch/_base/auto_quant_diagnostics_template.html
aimet_torch/_base/batch_norm_fold.py
aimet_torch/_base/mixed_precision.py
aimet_torch/_base/quant_analyzer.py
aimet_torch/_base/quantsim.py
aimet_torch/_base/seq_mse.py
aimet_torch/_base/adaround/__init__.py
aimet_torch/_base/adaround/activation_sampler.py
aimet_torch/_base/adaround/adaround_loss.py
aimet_torch/_base/adaround/adaround_optimizer.py
aimet_torch/_base/adaround/adaround_weight.py
aimet_torch/_base/adaround/adaround_wrapper.py
aimet_torch/_base/amp/__init__.py
aimet_torch/_base/amp/convert_ops_reduction.py
aimet_torch/_base/amp/mixed_precision_algo.py
aimet_torch-2.22.0.dist-info/METADATA
aimet_torch-2.22.0.dist-info/WHEEL
aimet_torch-2.22.0.dist-info/licenses/LICENSE
aimet_torch-2.22.0.dist-info/RECORD
