Metadata-Version: 2.2
Name: aimet-torch
Version: 2.22.0
Summary: AIMET torch package
Author: Qualcomm Innovation Center, Inc.
Author-Email: "Qualcomm Innovation Center, Inc." <aimet.os@quicinc.com>
License: BSD-3-Clause
Project-URL: Homepage, https://github.com/quic/aimet
Project-URL: Documentation, https://quic.github.io/aimet-pages/releases/latest/index.html
Requires-Python: >=3.10
Requires-Dist: Jinja2>=3.0.3
Requires-Dist: PyYAML
Requires-Dist: bokeh<=3.6.3
Requires-Dist: cvxpy
Requires-Dist: holoviews
Requires-Dist: hvplot
Requires-Dist: jsonschema
Requires-Dist: matplotlib>=3
Requires-Dist: networkx
Requires-Dist: numpy<2
Requires-Dist: onnx
Requires-Dist: onnxscript>=0.2.0
Requires-Dist: osqp
Requires-Dist: pandas
Requires-Dist: psutil
Requires-Dist: pybind11
Requires-Dist: safetensors
Requires-Dist: scikit-learn
Requires-Dist: scipy
Requires-Dist: tensorboard
Requires-Dist: torch
Requires-Dist: torchvision
Requires-Dist: tqdm
Provides-Extra: dev
Requires-Dist: scikit-build-core[wheels]==0.11.1; extra == "dev"
Provides-Extra: test
Requires-Dist: beautifulsoup4; extra == "test"
Requires-Dist: matplotlib; extra == "test"
Requires-Dist: onnx; extra == "test"
Requires-Dist: onnxruntime-extensions; extra == "test"
Requires-Dist: onnxsim; extra == "test"
Requires-Dist: peft; extra == "test"
Requires-Dist: pylint<3; extra == "test"
Requires-Dist: pytest; extra == "test"
Requires-Dist: pytest-xdist; extra == "test"
Requires-Dist: pytest-github-report; extra == "test"
Requires-Dist: pytorch-ignite; extra == "test"
Requires-Dist: safetensors<=0.5.3; extra == "test"
Requires-Dist: torchvision; extra == "test"
Requires-Dist: transformers<4.52.2; extra == "test"
Requires-Dist: accelerate<1.10.0; extra == "test"
Requires-Dist: datasets; extra == "test"
Requires-Dist: deepspeed<0.17.5; extra == "test"
Requires-Dist: onnxruntime; extra == "test"
Requires-Dist: spconv; extra == "test"
Provides-Extra: docs
Requires-Dist: furo; extra == "docs"
Requires-Dist: nbsphinx; extra == "docs"
Requires-Dist: pandoc; extra == "docs"
Requires-Dist: sphinx; extra == "docs"
Requires-Dist: sphinx-autodoc-typehints; extra == "docs"
Requires-Dist: sphinx-copybutton; extra == "docs"
Requires-Dist: sphinx-design; extra == "docs"
Requires-Dist: sphinx-jinja; extra == "docs"
Requires-Dist: sphinx-rtd-theme; extra == "docs"
Requires-Dist: sphinx-tabs; extra == "docs"
Provides-Extra: v1-deps
Requires-Dist: torch==2.1.*; extra == "v1-deps"
